qemu/__init__.py
qemu/__main__.py
qemu/main.py
qemu/qemu-riscv64
xuantie_qemu-20230825.dist-info/METADATA
xuantie_qemu-20230825.dist-info/WHEEL
xuantie_qemu-20230825.dist-info/entry_points.txt
xuantie_qemu-20230825.dist-info/top_level.txt
xuantie_qemu-20230825.dist-info/RECORD
