Metadata-Version: 2.1
Name: xuantie-qemu
Version: 20230825
Summary: QEMU from T-HEAD
Home-page: https://github.com/T-head-Semi/qemu
